requsim/__init__.py
requsim/events.py
requsim/noise.py
requsim/version.py
requsim/world.py
requsim/libs/__init__.py
requsim/libs/aux_functions.py
requsim/libs/epp.py
requsim/libs/matrix.py
requsim/quantum_objects/__init__.py
requsim/quantum_objects/pair.py
requsim/quantum_objects/qubit.py
requsim/quantum_objects/source.py
requsim/quantum_objects/station.py
requsim/quantum_objects/world_object.py
requsim/tools/__init__.py
requsim/tools/evaluation.py
requsim/tools/noise_channels.py
requsim/tools/protocol.py
requsim-0.4.dist-info/LICENSE
requsim-0.4.dist-info/METADATA
requsim-0.4.dist-info/WHEEL
requsim-0.4.dist-info/top_level.txt
requsim-0.4.dist-info/RECORD
