Metadata-Version: 2.1
Name: requsim
Version: 0.4
Summary: A simulation framework for quantum repeaters
Author: Julius Wallnöfer
License: MIT License
Project-URL: homepage, https://github.com/jwallnoefer/requsim
Keywords: quantum information,quantum information theory,quantum communication,quantum repeater
Classifier: License :: OSI Approved :: MIT License
Classifier: Programming Language :: Python :: 3
Classifier: Topic :: Scientific/Engineering :: Physics
Classifier: Intended Audience :: Science/Research
Requires-Python: >=3.8.10
Provides-Extra: test
Provides-Extra: docs
License-File: LICENSE
